RFML/RapidFireML.py
RFML/__init__.py
RFML/api/ServiceApi.py
RFML/api/__init__.py
RFML/channels/TelegramAgent.py
RFML/channels/__init__.py
RFML/core/CacheMixin.py
RFML/core/Cognitive.py
RFML/core/CognitiveModule.py
RFML/core/Conversation.py
RFML/core/Hosts.py
RFML/core/Interaction.py
RFML/core/Log.py
RFML/core/Meta.py
RFML/core/ModelCache.py
RFML/core/PromptCLI.py
RFML/core/Results.py
RFML/core/Router.py
RFML/core/SentenceFilterConfiguration.py
RFML/core/SentenceFilters.py
RFML/core/__init__.py
RFML/corpus/ContextCash.py
RFML/corpus/Corpus.py
RFML/corpus/CorpusAdaptors.py
RFML/corpus/CorpusBase.py
RFML/corpus/CorpusMapper.py
RFML/corpus/__init__.py
RFML/corpus/adaptors/MemoryDB.py
RFML/corpus/adaptors/MongoDB.py
RFML/corpus/adaptors/__init__.py
RFML/engines/__init__.py
RFML/engines/supervised/__init__.py
RFML/engines/supervised/NLP/__init__.py
RFML/engines/supervised/NLP/information_extraction/__init__.py
RFML/engines/supervised/NLP/information_extraction/command_extractor/CommandExtractor.py
RFML/engines/supervised/NLP/information_extraction/command_extractor/__init__.py
RFML/engines/supervised/NLP/information_extraction/command_extractor/corpus/CommandExtractionCorpus.py
RFML/engines/supervised/NLP/information_extraction/command_extractor/corpus/__init__.py
RFML/engines/supervised/NLP/information_extraction/command_extractor/handlers/Generator.py
RFML/engines/supervised/NLP/information_extraction/command_extractor/handlers/Predictor.py
RFML/engines/supervised/NLP/information_extraction/command_extractor/handlers/Trainer.py
RFML/engines/supervised/NLP/information_extraction/command_extractor/handlers/Validator.py
RFML/engines/supervised/NLP/information_extraction/command_extractor/handlers/__init__.py
RFML/engines/supervised/NLP/information_extraction/command_extractor/models/FakeModel.py
RFML/engines/supervised/NLP/information_extraction/command_extractor/models/__init__.py
RFML/engines/supervised/NLP/information_extraction/command_extractor/models/NER/IEBOT.py
RFML-0.0.17.dist-info/LICENSE.txt
RFML-0.0.17.dist-info/METADATA
RFML-0.0.17.dist-info/WHEEL
RFML-0.0.17.dist-info/top_level.txt
RFML-0.0.17.dist-info/RECORD
