Metadata-Version: 2.1
Name: RFML
Version: 0.0.17
Summary: RapidFire ML Library
Author-email: rbimrose@gmail.com
License-File: LICENSE.txt
Requires-Dist: pymongo
Requires-Dist: flask
Requires-Dist: spacy
Requires-Dist: torch
Requires-Dist: nltk
Requires-Dist: pyTelegramBotAPI
